sbapi_connect/__init__.py
sbapi_connect/connect.py
sbapi_connect/base/apibase.py
sbapi_connect/errors/apierrors.py
sbapi_connect-0.0.28.dist-info/METADATA
sbapi_connect-0.0.28.dist-info/WHEEL
sbapi_connect-0.0.28.dist-info/top_level.txt
sbapi_connect-0.0.28.dist-info/RECORD
