Metadata-Version: 2.4
Name: sbapi_connect
Version: 0.0.28
Summary: A small package to easier connect to Servebolt API
Author-email: "Oskar V. Hesle" <oskar@servebolt.com>
License-Expression: MIT
Project-URL: Homepage, http://servebolt.com
Classifier: Programming Language :: Python :: 3
Classifier: Operating System :: OS Independent
Requires-Python: >=3.9
Requires-Dist: requests
